{"id":10109,"name":"geodude-alola","dex":74,"genus":"Rock Pok\u00e9mon","names":{"ja-hrkt":"\u30a4\u30b7\u30c4\u30d6\u30c6","ja-roma":"Isitsubute","ko":"\uaf2c\ub9c8\ub3cc","zh-hant":"\u5c0f\u62f3\u77f3","fr":"Racaillou","de":"Kleinstein","es":"Geodude","it":"Geodude","en":"Geodude","ja":"\u30a4\u30b7\u30c4\u30d6\u30c6","zh-hans":"\u5c0f\u62f3\u77f3"},"ht":4,"wt":203,"exp":60,"types":["rock","electric"],"abils":[{"n":"magnet-pull","h":false,"s":1,"effect":"Prevents steel opponents from fleeing or switching out."},{"n":"sturdy","h":false,"s":2,"effect":"Prevents being KOed from full HP, leaving 1 HP instead.  Protects against the one-hit KO moves regardless of HP."},{"n":"galvanize","h":true,"s":3,"effect":"This Pok\u00e9mon's Normal moves are Electric and have their power increased to 1.2\u00d7."}],"stats":{"hp":40,"attack":80,"defense":100,"special_attack":30,"special_defense":30,"speed":20},"moves":{"tutor_ultra-sun-ultra-moon":[7,9,173,264,276,334,335,393,414,446,527],"machine_lets-go-pikachu-lets-go-eevee":[7,9,29,53,69,85,86,87,89,91,92,120,126,156,157,164,182,263,276,280,446],"machine_scarlet-violet":[7,9,34,36,38,53,85,86,87,89,91,126,156,157,164,174,182,189,201,203,214,241,263,264,268,280,317,334,341,350,360,374,414,444,446,451,479,521,523,527,528,667,851,916],"level-up_sun-moon":[[9,22],[33,1],[38,40],[88,16],[111,1],[120,24],[153,36],[205,10],[209,12],[268,4],[350,30],[397,6],[435,34],[444,42],[446,28],[479,18]],"level-up_ultra-sun-ultra-moon":[[9,22],[33,1],[38,40],[88,16],[111,1],[120,24],[153,36],[205,10],[209,12],[268,4],[350,30],[397,6],[435,34],[444,42],[446,28],[479,18]],"level-up_lets-go-pikachu-lets-go-eevee":[[9,27],[33,1],[36,15],[38,31],[84,3],[88,9],[111,1],[117,6],[120,19],[153,35],[157,23],[446,12]],"level-up_scarlet-violet":[[9,22],[33,1],[38,40],[88,16],[111,1],[120,24],[153,36],[205,10],[209,12],[268,4],[350,30],[397,6],[435,34],[444,42],[446,28],[479,18]],"machine_sun-moon":[53,85,87,89,92,104,126,153,156,157,164,182,201,207,213,214,216,218,237,241,263,267,280,317,360,374,397,444,451,479,496,521,523,590,693],"machine_ultra-sun-ultra-moon":[53,85,87,89,92,104,126,153,156,157,164,182,201,207,213,214,216,218,237,241,263,267,280,317,360,374,397,444,451,479,496,521,523,590,693],"egg_sun-moon":[68,103,174,175,203,335,393,431,469,475],"egg_ultra-sun-ultra-moon":[68,103,174,175,203,335,393,431,469,475],"egg_scarlet-violet":[68,103,174,175,192,203,335,469]},"species":"geodude","gen":"generation-i","leg":false,"myth":false,"baby":false,"eggs":["Mineral"],"flavor":[{"version":"red","text":"Found in fields and mountains. Mistaking them for boulders, people often step or trip on them."},{"version":"blue","text":"Found in fields and mountains. Mistaking them for boulders, people often step or trip on them."},{"version":"yellow","text":"Commonly found near mountain trails, etc. If you step on one by accident, it gets angry."},{"version":"gold","text":"Most people may not notice, but a closer look should reveal that there are many GEODUDE around."},{"version":"silver","text":"It uses its arms to steadily climb steep mountain paths. It swings its fists around if angered."},{"version":"crystal","text":"Proud of their sturdy bodies, they bash against each other in a contest to prove whose is harder."},{"version":"ruby","text":"The longer a GEODUDE lives, the more its edges are chipped and worn away, making it more rounded in appearance. However, this POK\u00e9MON\u2019s heart will remain hard, craggy, and rough always."},{"version":"sapphire","text":"When GEODUDE sleeps deeply, it buries itself halfway into the ground. It will not awaken even if hikers step on it unwittingly. In the morning, this POK\u00e9MON rolls downhill in search of food."},{"version":"emerald","text":"It climbs mountain paths using only the power of its arms. Because they look just like boulders lining paths, hikers may step on them without noticing."},{"version":"firered","text":"Its round form makes it easy to pick up. Some people have used them to hurl at each other in a snowball fight."},{"version":"leafgreen","text":"Found in fields and mountains. Mistaking them for boulders, people often step or trip on them."},{"version":"diamond","text":"Many live on mountain trails and remain half buried while keeping an eye on climbers."},{"version":"pearl","text":"It is impossible to distinguish from rocks. It slams against others in contests of hardness."},{"version":"platinum","text":"At rest, it looks just like a rock. Carelessly stepping on it will make it swing its fists angrily."},{"version":"heartgold","text":"Most people may not notice, but a closer look should reveal that there are many GEODUDE around."},{"version":"soulsilver","text":"It uses its arms to steadily climb steep mountain paths. It swings its fists around if angered."},{"version":"black","text":"At rest, it looks just like a rock. Carelessly stepping on it will make it swing its fists angrily."},{"version":"white","text":"At rest, it looks just like a rock. Carelessly stepping on it will make it swing its fists angrily."},{"version":"black-2","text":"At rest, it looks just like a rock. Carelessly stepping on it will make it swing its fists angrily."},{"version":"white-2","text":"At rest, it looks just like a rock. Carelessly stepping on it will make it swing its fists angrily."},{"version":"x","text":"Found in fields and mountains. Mistaking them for boulders, people often step or trip on them."},{"version":"y","text":"It is impossible to distinguish from rocks. It slams against others in contests of hardness."},{"version":"omega-ruby","text":"The longer a Geodude lives, the more its edges are chipped and worn away, making it more rounded in appearance. However, this Pok\u00e9mon\u2019s heart will remain hard, craggy, and rough always."},{"version":"alpha-sapphire","text":"When Geodude sleeps deeply, it buries itself halfway into the ground. It will not awaken even if hikers step on it unwittingly. In the morning, this Pok\u00e9mon rolls downhill in search of food."},{"version":"sun","text":"Its round body makes it easy to pick up, but it is hard and heavy. It\u2019s dangerous to play with them as if they were snowballs."},{"version":"moon","text":"There are plenty of them to be found along any road. A scholar with too much free time once counted a hundred of them along a single route."},{"version":"ultra-sun","text":"Geodude that have lived a long life have had all their edges smoothed out until they\u2019re totally round. They also have a calm, quiet disposition."},{"version":"ultra-moon","text":"It uses both hands to climb precipitous cliffs. People who see it in action have been known to take up bouldering."},{"version":"lets-go-pikachu","text":"Commonly found near mountain trails and the like. If you step on one by accident, it gets angry."},{"version":"lets-go-eevee","text":"Commonly found near mountain trails and the like. If you step on one by accident, it gets angry."},{"version":"legends-arceus","text":"Makes its home in mountainous regions, using its arms to climb along harsh mountain roads. Can be troublesome\u2014carelessly kicking one will cause it to fly into a rage and chase after you."}],"evo":{"name":"geodude","level":0,"min_level":null,"trigger":null,"item":null,"held_item":null,"known_move":null,"known_move_type":null,"location":null,"min_affection":null,"min_beauty":null,"min_happiness":null,"needs_overworld_rain":false,"time_of_day":null,"turn_upside_down":false,"evolves_to":[{"name":"graveler","level":1,"min_level":25,"trigger":"level-up","item":null,"held_item":null,"known_move":null,"known_move_type":null,"location":null,"min_affection":null,"min_beauty":null,"min_happiness":null,"needs_overworld_rain":false,"time_of_day":"","turn_upside_down":false,"evolves_to":[{"name":"golem","level":2,"min_level":null,"trigger":"trade","item":null,"held_item":null,"known_move":null,"known_move_type":null,"location":null,"min_affection":null,"min_beauty":null,"min_happiness":null,"needs_overworld_rain":false,"time_of_day":"","turn_upside_down":false,"evolves_to":[]}]}]},"sprite":"https://raw.githubusercontent.com/PokeAPI/sprites/master/sprites/pokemon/10109.png","shiny":"https://raw.githubusercontent.com/PokeAPI/sprites/master/sprites/pokemon/shiny/10109.png","capture":255,"happiness":70,"growth":"medium-slow","gender":4,"hatch":15,"ev":{"defense":1},"forms":[{"id":74,"name":"geodude","sprite":"https://raw.githubusercontent.com/PokeAPI/sprites/master/sprites/pokemon/74.png"}]}