{"id":1014,"name":"okidogi","dex":1014,"genus":"Retainer Pok\u00e9mon","names":{"ja-hrkt":"\u30a4\u30a4\u30cd\u30a4\u30cc","ko":"\uc870\ud0c0\uad6c","zh-hant":"\u5920\u8b9a\u72d7","fr":"F\u00e9licanis","de":"Boninu","es":"Okidogi","it":"Okidogi","en":"Okidogi","ja":"\u30a4\u30a4\u30cd\u30a4\u30cc","zh-hans":"\u591f\u8d5e\u72d7"},"ht":18,"wt":922,"exp":278,"types":["poison","fighting"],"abils":[{"n":"toxic-chain","h":false,"s":1,"effect":"May cause bad poisoning when the Pok\u00e9mon hits an opponent with a move."},{"n":"guard-dog","h":true,"s":3,"effect":"Boosts Attack if intimidated, and prevents being forced to switch out."}],"stats":{"hp":88,"attack":128,"defense":115,"special_attack":58,"special_defense":86,"speed":80},"moves":{"machine_scarlet-violet":[7,8,9,34,36,38,46,63,67,91,92,156,164,168,174,179,180,182,184,188,200,203,214,232,242,253,263,264,269,280,282,317,339,342,370,374,398,409,411,416,421,422,423,424,441,442,482,490,555,667,675,706,707,776,808,851,912,918],"level-up_scarlet-violet":[[44,1],[67,1],[68,32],[242,56],[276,64],[305,16],[336,8],[339,1],[395,24],[398,40],[416,72],[693,48]]},"species":"okidogi","gen":"generation-ix","leg":true,"myth":false,"baby":false,"eggs":["no-eggs"],"flavor":[{"version":"scarlet","text":"After all its muscles were stimulated by the toxic chain around its neck, Okidogi transformed and gained a powerful physique."},{"version":"violet","text":"Okidogi is a ruffian with a short temper. It can pulverize anything by swinging around the chain on its neck."}],"evo":{"name":"okidogi","level":0,"min_level":null,"trigger":null,"item":null,"held_item":null,"known_move":null,"known_move_type":null,"location":null,"min_affection":null,"min_beauty":null,"min_happiness":null,"needs_overworld_rain":false,"time_of_day":null,"turn_upside_down":false,"evolves_to":[]},"sprite":"https://raw.githubusercontent.com/PokeAPI/sprites/master/sprites/pokemon/1014.png","shiny":"https://raw.githubusercontent.com/PokeAPI/sprites/master/sprites/pokemon/shiny/1014.png","capture":3,"happiness":0,"growth":"slow","gender":-1,"hatch":50,"ev":{"attack":3},"forms":[]}