{"id":614,"name":"beartic","dex":614,"genus":"Freezing Pok\u00e9mon","names":{"ja-hrkt":"\u30c4\u30f3\u30d9\u30a2\u30fc","ja-roma":"Tunbear","ko":"\ud230\ubca0\uc5b4","zh-hant":"\u51cd\u539f\u718a","fr":"Polagriffe","de":"Siberio","es":"Beartic","it":"Beartic","en":"Beartic","ja":"\u30c4\u30f3\u30d9\u30a2\u30fc","zh-hans":"\u51bb\u539f\u718a"},"ht":26,"wt":2600,"exp":177,"types":["ice"],"abils":[{"n":"snow-cloak","h":false,"s":1,"effect":"Increases evasion to 1.25\u00d7 during hail.  Protects against hail damage."},{"n":"slush-rush","h":false,"s":2,"effect":"During Hail, this Pok\u00e9mon has double Speed."},{"n":"swift-swim","h":true,"s":3,"effect":"Doubles Speed during rain."}],"stats":{"hp":95,"attack":130,"defense":80,"special_attack":70,"special_defense":80,"speed":50},"moves":{"machine_sword-shield":[5,8,14,25,57,58,59,63,67,91,156,157,164,173,182,184,196,203,204,213,214,227,240,258,263,269,276,280,291,317,333,339,362,372,374,411,416,419,421,423,444,447,484,496,523,583,675,710,776],"tutor_black-2-white-2":[8,67,173,196,214,276,343],"tutor_omega-ruby-alpha-sapphire":[8,67,173,196,264,276,343,352],"tutor_ultra-sun-ultra-moon":[8,67,173,196,264,276,343,352,675],"machine_scarlet-violet":[8,14,34,36,38,46,57,58,59,63,67,89,91,156,157,164,168,174,179,182,184,189,196,203,204,214,227,232,240,242,263,264,269,280,283,317,332,333,339,341,352,370,374,404,411,416,419,421,423,444,447,484,523,555,583,675,710,776,851,883,885,886,912],"machine_black-white":[14,15,46,57,58,59,63,70,91,92,104,156,157,164,182,207,213,216,218,237,240,249,258,263,269,280,291,317,332,339,374,411,416,421,444,447,468,496,497,523,524],"machine_black-2-white-2":[14,15,46,57,58,59,63,70,91,92,104,156,157,164,182,207,213,216,218,237,240,249,258,263,269,280,291,317,332,339,374,411,416,421,444,447,468,496,497,523,524],"machine_x-y":[14,15,46,57,58,59,63,70,91,92,104,156,157,164,182,207,213,214,216,218,237,240,249,258,263,269,280,317,332,339,374,411,416,421,444,447,468,496,497,523,524,590,612],"machine_omega-ruby-alpha-sapphire":[14,15,46,57,58,59,63,70,91,92,104,156,157,164,182,207,213,214,216,218,237,240,249,258,263,269,280,290,291,317,332,339,374,411,416,421,444,447,468,496,497,523,524,590,612],"machine_sun-moon":[14,46,57,58,59,63,92,104,156,157,164,182,207,213,214,216,218,237,240,258,263,269,280,317,332,339,374,411,416,421,444,447,496,497,523,524,590],"machine_ultra-sun-ultra-moon":[14,46,57,58,59,63,92,104,156,157,164,182,207,213,214,216,218,237,240,258,263,269,280,317,332,339,374,411,416,421,444,447,496,497,523,524,590],"level-up_black-white":[[37,59],[45,1],[45,5],[59,45],[117,1],[117,9],[154,17],[156,41],[163,33],[175,36],[181,1],[196,1],[196,13],[203,25],[207,29],[258,53],[276,1],[329,66],[362,21],[556,37]],"level-up_black-2-white-2":[[37,59],[45,1],[45,5],[59,45],[117,1],[117,9],[154,17],[156,41],[163,33],[175,36],[181,1],[196,1],[196,13],[203,25],[207,29],[258,53],[276,1],[329,66],[362,21],[453,1],[556,37]],"level-up_x-y":[[37,1],[37,59],[45,1],[59,45],[117,1],[154,17],[156,41],[163,33],[175,36],[181,1],[196,1],[196,13],[203,25],[207,29],[258,53],[276,1],[329,1],[329,66],[362,21],[453,1],[556,37],[589,9]],"level-up_omega-ruby-alpha-sapphire":[[37,1],[37,59],[45,1],[59,45],[117,1],[154,17],[156,41],[163,33],[175,36],[181,1],[196,1],[196,13],[203,25],[207,29],[258,53],[276,1],[329,1],[329,66],[362,21],[453,1],[556,37],[589,9]],"level-up_sun-moon":[[37,1],[37,59],[45,1],[59,45],[117,1],[117,9],[154,17],[156,41],[163,33],[175,36],[181,1],[181,5],[196,1],[196,13],[203,25],[207,29],[258,53],[276,1],[329,1],[329,66],[362,21],[453,1],[556,0],[556,1],[589,15]],"level-up_ultra-sun-ultra-moon":[[37,1],[37,59],[45,1],[59,45],[117,1],[117,9],[154,17],[156,41],[163,33],[175,36],[181,1],[181,5],[196,1],[196,13],[203,25],[207,29],[258,53],[276,1],[329,1],[329,66],[362,21],[453,1],[556,0],[556,1],[589,15]],"level-up_sword-shield":[[37,33],[45,1],[59,41],[154,1],[156,36],[163,21],[175,24],[181,1],[196,9],[203,1],[204,1],[207,27],[258,30],[276,51],[329,46],[362,15],[453,1],[524,18],[556,0],[556,1],[589,12]],"level-up_scarlet-violet":[[37,33],[45,1],[59,41],[154,1],[156,36],[163,21],[175,24],[181,1],[196,9],[203,1],[204,1],[207,27],[276,51],[329,46],[362,15],[453,1],[524,18],[556,0],[589,12],[883,30]]},"species":"beartic","gen":"generation-v","leg":false,"myth":false,"baby":false,"eggs":["Field"],"flavor":[{"version":"black","text":"It can make its breath freeze at will. Very able in the water, it swims around in northern seas and catches prey."},{"version":"white","text":"It freezes its breath to create fangs and claws of ice to fight with. Cold northern areas are its habitat."},{"version":"black-2","text":"They love the cold seas of the north. They create pathways across the ocean waters by freezing their own breath."},{"version":"white-2","text":"They love the cold seas of the north. They create pathways across the ocean waters by freezing their own breath."},{"version":"x","text":"They love the cold seas of the north. They create pathways across the ocean waters by freezing their own breath."},{"version":"y","text":"It freezes its breath to create fangs and claws of ice to fight with. Cold northern areas are its habitat."},{"version":"omega-ruby","text":"They love the cold seas of the north. They create pathways across the ocean waters by freezing their own breath."},{"version":"alpha-sapphire","text":"It freezes its breath to create fangs and claws of ice to fight with. Cold northern areas are its habitat."},{"version":"sword","text":"It swims through frigid seas, searching for prey. From its frozen breath, it forms icy fangs that are harder than steel."},{"version":"shield","text":"It swims energetically through frigid seas. When it gets tired, it freezes the seawater with its breath so it can rest on the ice."}],"evo":{"name":"cubchoo","level":0,"min_level":null,"trigger":null,"item":null,"held_item":null,"known_move":null,"known_move_type":null,"location":null,"min_affection":null,"min_beauty":null,"min_happiness":null,"needs_overworld_rain":false,"time_of_day":null,"turn_upside_down":false,"evolves_to":[{"name":"beartic","level":1,"min_level":37,"trigger":"level-up","item":null,"held_item":null,"known_move":null,"known_move_type":null,"location":null,"min_affection":null,"min_beauty":null,"min_happiness":null,"needs_overworld_rain":false,"time_of_day":"","turn_upside_down":false,"evolves_to":[]}]},"sprite":"https://raw.githubusercontent.com/PokeAPI/sprites/master/sprites/pokemon/614.png","shiny":"https://raw.githubusercontent.com/PokeAPI/sprites/master/sprites/pokemon/shiny/614.png","capture":60,"happiness":70,"growth":"medium","gender":4,"hatch":20,"ev":{"attack":2},"forms":[]}