{"id":701,"name":"hawlucha","dex":701,"genus":"Wrestling Pok\u00e9mon","names":{"ja-hrkt":"\u30eb\u30c1\u30e3\u30d6\u30eb","ja-roma":"Luchabull","ko":"\ub8e8\ucc28\ubd88","zh-hant":"\u6454\u89d2\u9df9\u4eba","fr":"Brutalibr\u00e9","de":"Resladero","es":"Hawlucha","it":"Hawlucha","en":"Hawlucha","ja":"\u30eb\u30c1\u30e3\u30d6\u30eb","zh-hans":"\u6454\u89d2\u9e70\u4eba"},"ht":8,"wt":215,"exp":175,"types":["fighting","flying"],"abils":[{"n":"limber","h":false,"s":1,"effect":"Prevents paralysis."},{"n":"unburden","h":false,"s":2,"effect":"Doubles Speed upon using or losing a held item."},{"n":"mold-breaker","h":true,"s":3,"effect":"Bypasses targets' abilities if they could hinder or prevent a move."}],"stats":{"hp":78,"attack":92,"defense":75,"special_attack":74,"special_defense":63,"speed":118},"moves":{"level-up_x-y":[[2,4],[14,60],[17,8],[33,1],[136,44],[143,48],[197,1],[227,20],[283,36],[297,40],[332,16],[340,32],[355,12],[374,24],[468,1],[507,55],[560,28]],"level-up_omega-ruby-alpha-sapphire":[[2,4],[14,60],[17,8],[33,1],[136,44],[143,48],[197,1],[227,20],[283,36],[297,40],[332,16],[340,32],[355,12],[374,24],[468,1],[507,55],[560,28]],"level-up_sun-moon":[[2,4],[14,60],[17,8],[33,1],[136,44],[143,48],[197,1],[227,20],[283,36],[297,40],[332,16],[340,32],[355,12],[374,24],[468,1],[507,55],[560,28]],"level-up_ultra-sun-ultra-moon":[[2,4],[14,60],[17,8],[33,1],[136,44],[143,48],[197,1],[227,20],[283,36],[297,40],[332,16],[340,32],[355,12],[374,24],[468,1],[507,55],[560,28]],"machine_sword-shield":[5,7,9,14,19,25,67,91,97,129,156,157,164,173,179,182,203,206,211,213,214,226,227,240,241,263,269,270,276,279,280,317,339,340,369,370,371,372,374,398,404,409,411,413,416,428,442,444,447,490,496,502,512,514,526,675,776],"tutor_omega-ruby-alpha-sapphire":[7,9,67,143,173,264,270,276,283,340,366,387,409,428,442,530],"tutor_ultra-sun-ultra-moon":[7,9,67,143,173,264,270,276,283,340,366,387,409,428,432,442,502,530,673,675],"machine_scarlet-violet":[7,9,14,19,34,36,63,67,91,97,129,156,157,164,168,179,182,203,206,214,226,227,240,241,253,263,264,269,270,280,283,297,317,332,339,369,370,374,398,404,409,411,413,416,428,442,444,447,490,512,675,679,776,811,814,851,885,918],"machine_x-y":[14,15,19,70,91,92,104,156,157,164,182,206,207,211,213,214,216,218,237,240,241,249,259,263,269,280,317,332,339,355,369,371,374,398,404,411,416,444,447,468,490,496,507,512,514,590,612],"machine_omega-ruby-alpha-sapphire":[14,15,19,70,91,92,104,156,157,164,182,206,207,211,213,214,216,218,237,240,241,249,259,263,269,280,290,317,332,339,355,369,371,374,398,404,411,416,444,447,468,490,496,507,512,514,590,612],"machine_sun-moon":[14,19,92,104,156,157,164,182,206,207,211,213,214,216,218,237,240,241,259,263,269,280,317,332,339,355,369,371,374,398,404,411,416,444,447,490,496,507,512,526,590],"machine_ultra-sun-ultra-moon":[14,19,92,104,156,157,164,182,206,207,211,213,214,216,218,237,240,241,259,263,269,280,317,332,339,355,369,371,374,398,404,411,416,444,447,490,496,507,512,526,590],"level-up_sword-shield":[[14,40],[17,4],[33,1],[66,24],[136,48],[143,56],[197,8],[227,16],[269,32],[283,52],[297,20],[332,12],[340,28],[355,36],[468,1],[560,44]],"level-up_scarlet-violet":[[14,40],[17,4],[33,1],[136,48],[143,56],[197,8],[227,16],[269,32],[280,24],[283,52],[297,20],[332,12],[340,28],[355,36],[468,1],[560,44]],"egg_x-y":[97,226,300,382,494,501,502],"egg_omega-ruby-alpha-sapphire":[97,226,300,382,494,501,502],"egg_sun-moon":[97,226,300,382,494,501,502],"egg_ultra-sun-ultra-moon":[97,226,300,364,382,494,501,502],"egg_sword-shield":[212,238,364,432,494,501],"egg_scarlet-violet":[212,238,364,432,494,501],"tutor_sword-shield":[811,814]},"species":"hawlucha","gen":"generation-vi","leg":false,"myth":false,"baby":false,"eggs":["Flying","Human-Like"],"flavor":[{"version":"x","text":"Although its body is small, its proficient fighting skills enable it to keep up with big bruisers like Machamp and Hariyama."},{"version":"y","text":"With its wings, it controls its position in the air. It likes to attack from above, a maneuver that is difficult to defend against."},{"version":"omega-ruby","text":"Although its body is small, its proficient fighting skills enable it to keep up with big bruisers like Machamp and Hariyama."},{"version":"alpha-sapphire","text":"With its wings, it controls its position in the air. It likes to attack from above, a maneuver that is difficult to defend against."},{"version":"ultra-sun","text":"It overwhelms opponents with quick moves, but sometimes it showboats for too long when it\u2019s using a special move and gets itself into a pinch."},{"version":"ultra-moon","text":"In combat, Hawlucha leaps nimbly about, taking advantage of its opponents\u2019 blind spots. It\u2019s also skilled at using superb submission holds."},{"version":"sword","text":"It drives its opponents to exhaustion with its agile maneuvers, then ends the fight with a flashy finishing move."},{"version":"shield","text":"It always strikes a pose before going for its finishing move. Sometimes opponents take advantage of that time to counterattack."}],"evo":{"name":"hawlucha","level":0,"min_level":null,"trigger":null,"item":null,"held_item":null,"known_move":null,"known_move_type":null,"location":null,"min_affection":null,"min_beauty":null,"min_happiness":null,"needs_overworld_rain":false,"time_of_day":null,"turn_upside_down":false,"evolves_to":[]},"sprite":"https://raw.githubusercontent.com/PokeAPI/sprites/master/sprites/pokemon/701.png","shiny":"https://raw.githubusercontent.com/PokeAPI/sprites/master/sprites/pokemon/shiny/701.png","capture":100,"happiness":70,"growth":"medium","gender":4,"hatch":20,"ev":{"attack":2},"forms":[{"id":10300,"name":"hawlucha-mega","sprite":"https://raw.githubusercontent.com/PokeAPI/sprites/master/sprites/pokemon/10300.png"}]}