{"id":792,"name":"lunala","dex":792,"genus":"Moone Pok\u00e9mon","names":{"ja-hrkt":"\u30eb\u30ca\u30a2\u30fc\u30e9","ja-roma":"Lunala","ko":"\ub8e8\ub098\uc544\ub77c","zh-hant":"\u9732\u5948\u96c5\u62c9","fr":"Lunala","de":"Lunala","es":"Lunala","it":"Lunala","en":"Lunala","ja":"\u30eb\u30ca\u30a2\u30fc\u30e9","zh-hans":"\u9732\u5948\u96c5\u62c9"},"ht":40,"wt":1200,"exp":306,"types":["psychic","ghost"],"abils":[{"n":"shadow-shield","h":false,"s":1,"effect":"When this Pok\u00e9mon has full HP, regular damage from moves is halved."}],"stats":{"hp":137,"attack":113,"defense":89,"special_attack":137,"special_defense":107,"speed":97},"moves":{"machine_sun-moon":[19,46,58,59,63,76,85,86,87,92,94,104,113,115,138,156,164,182,207,214,216,218,219,237,241,244,247,261,263,332,347,355,411,416,421,433,451,473,496,507,512,526,590,605],"machine_ultra-sun-ultra-moon":[19,46,58,59,63,76,85,86,87,92,94,104,113,115,138,156,164,182,207,214,216,218,219,237,241,244,247,261,263,332,347,355,411,416,421,433,451,473,496,507,512,526,590,605],"machine_sword-shield":[19,58,59,63,76,85,86,87,94,97,113,115,129,156,164,173,182,184,196,203,214,219,241,247,248,257,261,263,270,271,322,347,403,411,416,421,427,433,472,473,478,496,506,512,526,566,605],"machine_scarlet-violet":[19,58,59,63,76,85,87,94,97,101,109,113,115,129,156,164,180,182,184,196,203,214,240,241,244,247,248,257,261,263,270,271,332,347,366,403,411,416,421,433,451,473,506,512,566,605,797,800,809,814,851],"level-up_sun-moon":[[63,73],[93,1],[95,1],[100,1],[101,7],[109,13],[138,59],[236,31],[247,23],[277,43],[322,1],[403,19],[469,67],[539,37],[566,61],[585,47],[714,0],[714,1]],"level-up_ultra-sun-ultra-moon":[[63,73],[93,1],[95,1],[100,1],[101,7],[109,13],[138,59],[236,31],[247,23],[277,43],[322,1],[403,19],[469,67],[539,37],[566,61],[585,47],[714,0],[714,1]],"level-up_sword-shield":[[63,84],[93,1],[95,1],[100,1],[101,7],[109,14],[138,70],[236,35],[247,28],[277,49],[322,1],[403,21],[469,77],[539,42],[566,63],[585,56],[714,0],[714,1]],"level-up_scarlet-violet":[[93,1],[94,49],[95,1],[100,1],[101,7],[109,14],[138,70],[236,35],[247,28],[322,1],[403,21],[469,77],[539,42],[566,63],[585,56],[714,0]],"tutor_ultra-sun-ultra-moon":[143,173,180,196,257,271,277,324,351,366,432,472,477,478],"tutor_sword-shield":[797,800,809,814]},"species":"lunala","gen":"generation-vii","leg":true,"myth":false,"baby":false,"eggs":["no-eggs"],"flavor":[{"version":"sun","text":"It is said to be a female evolution of Cosmog. When its third eye activates, away it flies to another world."},{"version":"moon","text":"Said to live in another world, this Pok\u00e9mon devours light, drawing the moonless dark veil of night over the brightness of day."},{"version":"ultra-sun","text":"Records of it exist in writings from long, long ago, where it was known by the name \u201cthe beast that calls the moon.\u201d"},{"version":"ultra-moon","text":"It sometimes summons unknown powers and life-forms here to this world from holes that lead to other worlds."},{"version":"sword","text":"Known as the Beast That Calls the Moon, this Pok\u00e9mon lives by taking in any and all light and converting it into its own energy."},{"version":"shield","text":"It steals the light from its surroundings and then becomes the full moon, showering its own light across the night sky."}],"evo":{"name":"cosmog","level":0,"min_level":null,"trigger":null,"item":null,"held_item":null,"known_move":null,"known_move_type":null,"location":null,"min_affection":null,"min_beauty":null,"min_happiness":null,"needs_overworld_rain":false,"time_of_day":null,"turn_upside_down":false,"evolves_to":[{"name":"cosmoem","level":1,"min_level":43,"trigger":"level-up","item":null,"held_item":null,"known_move":null,"known_move_type":null,"location":null,"min_affection":null,"min_beauty":null,"min_happiness":null,"needs_overworld_rain":false,"time_of_day":"","turn_upside_down":false,"evolves_to":[{"name":"solgaleo","level":2,"min_level":53,"trigger":"level-up","item":null,"held_item":null,"known_move":null,"known_move_type":null,"location":null,"min_affection":null,"min_beauty":null,"min_happiness":null,"needs_overworld_rain":false,"time_of_day":"","turn_upside_down":false,"evolves_to":[]},{"name":"lunala","level":2,"min_level":53,"trigger":"level-up","item":null,"held_item":null,"known_move":null,"known_move_type":null,"location":null,"min_affection":null,"min_beauty":null,"min_happiness":null,"needs_overworld_rain":false,"time_of_day":"","turn_upside_down":false,"evolves_to":[]}]}]},"sprite":"https://raw.githubusercontent.com/PokeAPI/sprites/master/sprites/pokemon/792.png","shiny":"https://raw.githubusercontent.com/PokeAPI/sprites/master/sprites/pokemon/shiny/792.png","capture":45,"happiness":0,"growth":"slow","gender":-1,"hatch":120,"ev":{"special_attack":3},"forms":[]}