{"id":793,"name":"nihilego","dex":793,"genus":"Parasite Pok\u00e9mon","names":{"ja-hrkt":"\u30a6\u30c4\u30ed\u30a4\u30c9","ja-roma":"Uturoid","ko":"\ud145\ube44\ub4dc","zh-hant":"\u865b\u543e\u4f0a\u5fb7","fr":"Z\u00e9ro\u00efd","de":"Anego","es":"Nihilego","it":"Nihilego","en":"Nihilego","ja":"\u30a6\u30c4\u30ed\u30a4\u30c9","zh-hans":"\u865a\u543e\u4f0a\u5fb7"},"ht":12,"wt":555,"exp":257,"types":["rock","poison"],"abils":[{"n":"beast-boost","h":false,"s":1,"effect":"Raises this Pok\u00e9mon's highest stat by one stage when it faints another Pok\u00e9mon."}],"stats":{"hp":109,"attack":53,"defense":47,"special_attack":127,"special_defense":131,"speed":103},"moves":{"level-up_sun-moon":[[1,1],[29,19],[51,1],[132,1],[149,13],[219,31],[243,43],[321,1],[390,29],[408,37],[446,59],[457,73],[470,1],[471,1],[472,67],[474,23],[491,47],[499,7],[599,53]],"level-up_ultra-sun-ultra-moon":[[1,1],[29,19],[51,1],[132,1],[149,13],[219,31],[243,43],[321,1],[390,29],[408,37],[446,59],[457,73],[470,1],[471,1],[472,67],[474,23],[491,47],[499,7],[599,53]],"level-up_sword-shield":[[1,1],[29,35],[35,1],[51,5],[243,60],[321,10],[390,40],[408,50],[446,55],[457,70],[470,25],[471,25],[472,65],[474,30],[491,15],[499,20],[599,45]],"tutor_ultra-sun-ultra-moon":[20,173,180,220,272,277,282,388,428,441,442,446,472,477,492,502],"machine_sword-shield":[34,85,86,87,94,113,156,157,164,173,182,188,201,203,214,219,263,317,390,398,408,428,433,440,441,442,446,447,472,473,474,482,492,496,502,506,599,605,693],"machine_sun-moon":[85,86,87,92,94,104,113,115,156,164,182,188,201,207,214,216,218,219,237,263,398,433,447,451,473,474,482,496,497,590,605,693],"machine_ultra-sun-ultra-moon":[85,86,87,92,94,104,113,115,156,164,182,188,201,207,214,216,218,219,237,263,398,433,447,451,473,474,482,496,497,590,605,693],"tutor_sword-shield":[800,810]},"species":"nihilego","gen":"generation-vii","leg":false,"myth":false,"baby":false,"eggs":["no-eggs"],"flavor":[{"version":"sun","text":"One of several mysterious Ultra Beasts. People on the street report observing those infested by it suddenly becoming violent."},{"version":"moon","text":"One of the Ultra Beasts. It\u2019s unclear whether or not this Pok\u00e9mon is sentient, but sometimes it can be observed behaving like a young girl."},{"version":"ultra-sun","text":"A life-form from another world, it was dubbed a UB and is thought to produce a strong neurotoxin."},{"version":"ultra-moon","text":"It appeared in this world from an Ultra Wormhole. Nihilego appears to be a parasite that lives by feeding on people and Pok\u00e9mon."}],"evo":{"name":"nihilego","level":0,"min_level":null,"trigger":null,"item":null,"held_item":null,"known_move":null,"known_move_type":null,"location":null,"min_affection":null,"min_beauty":null,"min_happiness":null,"needs_overworld_rain":false,"time_of_day":null,"turn_upside_down":false,"evolves_to":[]},"sprite":"https://raw.githubusercontent.com/PokeAPI/sprites/master/sprites/pokemon/793.png","shiny":"https://raw.githubusercontent.com/PokeAPI/sprites/master/sprites/pokemon/shiny/793.png","capture":45,"happiness":0,"growth":"slow","gender":-1,"hatch":120,"ev":{"special_defense":3},"forms":[]}