{"id":829,"name":"gossifleur","dex":829,"genus":"Flowering Pok\u00e9mon","names":{"ja-hrkt":"\u30d2\u30e1\u30f3\u30ab","ja-roma":"Himenka","ko":"\uaf2c\ubaa8\uce74","zh-hant":"\u5e7c\u68c9\u68c9","fr":"Tournicoton","de":"Cottini","es":"Gossifleur","it":"Gossifleur","en":"Gossifleur","ja":"\u30d2\u30e1\u30f3\u30ab","zh-hans":"\u5e7c\u68c9\u68c9"},"ht":4,"wt":22,"exp":50,"types":["grass"],"abils":[{"n":"cotton-down","h":false,"s":1,"effect":"When Ignores moves and abilities that draw in moves."},{"n":"regenerator","h":false,"s":2,"effect":"Heals for 1/3 max HP upon switching out."},{"n":"effect-spore","h":true,"s":3,"effect":"Has a 30% chance of inflcting either paralysis, poison, or sleep on attacking Pok\u00e9mon on contact."}],"stats":{"hp":40,"attack":40,"defense":60,"special_attack":40,"special_defense":60,"speed":10},"moves":{"level-up_sword-shield":[[47,1],[75,12],[229,4],[230,8],[235,24],[304,28],[312,32],[437,36],[496,16],[536,21],[670,1]],"egg_sword-shield":[73,74,77,78,79,388],"machine_sword-shield":[76,113,156,164,173,182,202,203,204,213,214,241,263,270,304,331,345,412,437,447,496,580,676],"tutor_sword-shield":[803]},"species":"gossifleur","gen":"generation-viii","leg":false,"myth":false,"baby":false,"eggs":["Grass"],"flavor":[{"version":"sword","text":"It anchors itself in the ground with its single leg, then basks in the sun. After absorbing enough sunlight, its petals spread as it blooms brilliantly."},{"version":"shield","text":"It whirls around in the wind while singing a joyous song. This delightful display has charmed many into raising this Pok\u00e9mon."}],"evo":{"name":"gossifleur","level":0,"min_level":null,"trigger":null,"item":null,"held_item":null,"known_move":null,"known_move_type":null,"location":null,"min_affection":null,"min_beauty":null,"min_happiness":null,"needs_overworld_rain":false,"time_of_day":null,"turn_upside_down":false,"evolves_to":[{"name":"eldegoss","level":1,"min_level":20,"trigger":"level-up","item":null,"held_item":null,"known_move":null,"known_move_type":null,"location":null,"min_affection":null,"min_beauty":null,"min_happiness":null,"needs_overworld_rain":false,"time_of_day":"","turn_upside_down":false,"evolves_to":[]}]},"sprite":"https://raw.githubusercontent.com/PokeAPI/sprites/master/sprites/pokemon/829.png","shiny":"https://raw.githubusercontent.com/PokeAPI/sprites/master/sprites/pokemon/shiny/829.png","capture":190,"happiness":50,"growth":"medium","gender":4,"hatch":20,"ev":{"special_defense":1},"forms":[]}