{"id":874,"name":"stonjourner","dex":874,"genus":"Big Rock Pok\u00e9mon","names":{"ja-hrkt":"\u30a4\u30b7\u30d8\u30f3\u30b8\u30f3","ja-roma":"Ishihengin","ko":"\ub3cc\ud5e8\uc9c4","zh-hant":"\u5de8\u77f3\u4e01","fr":"Dolman","de":"Humanolith","es":"Stonjourner","it":"Stonjourner","en":"Stonjourner","ja":"\u30a4\u30b7\u30d8\u30f3\u30b8\u30f3","zh-hans":"\u5de8\u77f3\u4e01"},"ht":25,"wt":5200,"exp":165,"types":["rock"],"abils":[{"n":"power-spot","h":false,"s":1,"effect":"Just being next to the Pok\u00e9mon powers up moves."}],"stats":{"hp":100,"attack":125,"defense":135,"special_attack":20,"special_defense":20,"speed":70},"moves":{"level-up_sword-shield":[[23,24],[25,66],[34,42],[88,1],[157,36],[317,12],[335,1],[356,18],[397,6],[444,60],[446,30],[469,48],[484,54]],"level-up_scarlet-violet":[[23,24],[25,66],[34,42],[88,1],[157,36],[317,12],[335,1],[356,18],[397,6],[444,60],[446,30],[469,48],[484,54]],"machine_sword-shield":[25,34,63,89,120,156,157,164,173,182,201,203,213,214,219,263,276,286,317,328,334,350,372,414,416,444,446,472,484,496,523,535,693,707,776],"machine_scarlet-violet":[34,36,63,67,89,156,157,164,174,182,201,203,214,241,244,263,283,286,317,328,334,350,356,408,414,416,444,446,479,484,490,523,535,667,707,776,800,851,912],"egg_sword-shield":[174,246],"egg_scarlet-violet":[174,246],"tutor_sword-shield":[800]},"species":"stonjourner","gen":"generation-viii","leg":false,"myth":false,"baby":false,"eggs":["Mineral"],"flavor":[{"version":"sword","text":"It stands in grasslands, watching the sun\u2019s descent from zenith to horizon. This Pok\u00e9mon has a talent for delivering dynamic kicks."},{"version":"shield","text":"Once a year, on a specific date and at a specific time, they gather out of nowhere and form up in a circle."}],"evo":{"name":"stonjourner","level":0,"min_level":null,"trigger":null,"item":null,"held_item":null,"known_move":null,"known_move_type":null,"location":null,"min_affection":null,"min_beauty":null,"min_happiness":null,"needs_overworld_rain":false,"time_of_day":null,"turn_upside_down":false,"evolves_to":[]},"sprite":"https://raw.githubusercontent.com/PokeAPI/sprites/master/sprites/pokemon/874.png","shiny":"https://raw.githubusercontent.com/PokeAPI/sprites/master/sprites/pokemon/shiny/874.png","capture":60,"happiness":50,"growth":"slow","gender":4,"hatch":25,"ev":{"defense":2},"forms":[]}